F1_lap_time_telementary/__init__.py
F1_lap_time_telementary/visualization.py
F1_lap_time_telementary/Examples/compare_qualifying.py
fastf1plot-0.1.0.dist-info/licenses/LICENSE
fastf1plot-0.1.0.dist-info/METADATA
fastf1plot-0.1.0.dist-info/WHEEL
fastf1plot-0.1.0.dist-info/top_level.txt
fastf1plot-0.1.0.dist-info/RECORD
