Metadata-Version: 2.4
Name: fastf1plot
Version: 0.1.0
Summary: Plot F1 telemetry data using FastF1
Author-email: Sidhartha Kumar <siddkumar718@gmail.com>
License: MIT
License-File: LICENSE
Requires-Dist: fastf1>=3.0.0
Requires-Dist: matplotlib>=3.0
Dynamic: license-file
